calculadora/__init__.py
calculadora_python_2020ibsi0435_ifes-0.1.2.dist-info/licenses/LICENSE
calculadora_python_2020ibsi0435_ifes-0.1.2.dist-info/METADATA
calculadora_python_2020ibsi0435_ifes-0.1.2.dist-info/WHEEL
calculadora_python_2020ibsi0435_ifes-0.1.2.dist-info/top_level.txt
calculadora_python_2020ibsi0435_ifes-0.1.2.dist-info/RECORD
