Metadata-Version: 2.4
Name: calculadora-python-2020ibsi0435-ifes
Version: 0.1.2
Summary: Uma calculadora com API FastAPI
Author: Matthew A.
Author-email: ecshestagioclik@gmail.com
Classifier: Programming Language :: Python :: 3
Classifier: Framework :: FastAPI
Classifier: Operating System :: OS Independent
Requires-Python: >=3.8
License-File: LICENSE
Requires-Dist: fastapi
Requires-Dist: uvicorn
Requires-Dist: pydantic
Dynamic: author
Dynamic: author-email
Dynamic: classifier
Dynamic: license-file
Dynamic: requires-dist
Dynamic: requires-python
Dynamic: summary
